integration_test/cluster_test/__init__.py
integration_test/cluster_test/base_env.py
integration_test/cluster_test/component.py
integration_test/cluster_test/conftest.py
integration_test/cluster_test/test_cluster.py
integration_test/fake_cluster/__init__.py
libmuscle/__init__.py
libmuscle/api_guard.py
libmuscle/checkpoint_triggers.py
libmuscle/communicator.py
libmuscle/endpoint.py
libmuscle/errors.py
libmuscle/grid.py
libmuscle/instance.py
libmuscle/logging.py
libmuscle/logging_handler.py
libmuscle/mmp_client.py
libmuscle/mmsf_validator.py
libmuscle/mpp_client.py
libmuscle/mpp_message.py
libmuscle/mpp_server.py
libmuscle/outbox.py
libmuscle/peer_info.py
libmuscle/port.py
libmuscle/port_manager.py
libmuscle/post_office.py
libmuscle/profiler.py
libmuscle/profiling.py
libmuscle/py.typed
libmuscle/receive_timeout_handler.py
libmuscle/runner.py
libmuscle/settings_manager.py
libmuscle/snapshot.py
libmuscle/snapshot_manager.py
libmuscle/timestamp.py
libmuscle/util.py
libmuscle/version.py
libmuscle/manager/__init__.py
libmuscle/manager/deadlock_detector.py
libmuscle/manager/instance_manager.py
libmuscle/manager/instance_registry.py
libmuscle/manager/instantiator.py
libmuscle/manager/logger.py
libmuscle/manager/manager.py
libmuscle/manager/mmp_server.py
libmuscle/manager/profile_database.py
libmuscle/manager/profile_store.py
libmuscle/manager/run_dir.py
libmuscle/manager/snapshot_registry.py
libmuscle/manager/topology_store.py
libmuscle/manager/test/__init__.py
libmuscle/manager/test/conftest.py
libmuscle/manager/test/test_deadlock_detector.py
libmuscle/manager/test/test_instance_registry.py
libmuscle/manager/test/test_logger.py
libmuscle/manager/test/test_mmp_request_handler.py
libmuscle/manager/test/test_profile_database.py
libmuscle/manager/test/test_profile_store.py
libmuscle/manager/test/test_snapshot_registry.py
libmuscle/manager/test/test_topology_store.py
libmuscle/mcp/__init__.py
libmuscle/mcp/protocol.py
libmuscle/mcp/tcp_transport_client.py
muscle3-0.8.0.dist-info/LICENSE
muscle3-0.8.0.dist-info/METADATA
muscle3-0.8.0.dist-info/NOTICE
muscle3-0.8.0.dist-info/WHEEL
muscle3-0.8.0.dist-info/entry_points.txt
muscle3-0.8.0.dist-info/top_level.txt
muscle3-0.8.0.dist-info/RECORD
