Metadata-Version: 2.1
Name: muscle3
Version: 0.8.0
Summary: Version 3 of the MUltiScale Coupling Library and Environment
Home-page: https://github.com/multiscale/muscle3
Author: Lourens Veen
Author-email: l.veen@esciencecenter.nl
License: Apache License 2.0
Keywords: multiscale,coupling,MUSCLE
Classifier: Development Status :: 4 - Beta
Classifier: License :: OSI Approved :: Apache Software License
Classifier: Operating System :: POSIX :: Linux
Classifier: Programming Language :: Python :: 3.8
Classifier: Programming Language :: Python :: 3.9
Classifier: Programming Language :: Python :: 3.10
Classifier: Programming Language :: Python :: 3.11
Classifier: Programming Language :: Python :: 3.12
Classifier: Programming Language :: Python :: 3.13
Requires-Python: >=3.8, <4
License-File: LICENSE
License-File: NOTICE
Requires-Dist: click<9,>=7.1
Requires-Dist: matplotlib<4,>=3
Requires-Dist: msgpack<2,>=1
Requires-Dist: psutil>=5.0.0
Requires-Dist: parsimonious
Requires-Dist: numpy>=1.22
Requires-Dist: ymmsl<0.15,>=0.14.0
Provides-Extra: dev
Requires-Dist: tox; extra == "dev"
